drf_openapi/__init__.py
drf_openapi/apps.py
drf_openapi/codec.py
drf_openapi/entities.py
drf_openapi/urls.py
drf_openapi/utils.py
drf_openapi/views.py
drf_openapi/templates/drf_openapi/index.html
drf_openapi-1.3.0.dist-info/DESCRIPTION.rst
drf_openapi-1.3.0.dist-info/METADATA
drf_openapi-1.3.0.dist-info/RECORD
drf_openapi-1.3.0.dist-info/WHEEL
drf_openapi-1.3.0.dist-info/entry_points.txt
drf_openapi-1.3.0.dist-info/metadata.json
drf_openapi-1.3.0.dist-info/top_level.txt
