Metadata-Version: 2.0
Name: drf-openapi
Version: 1.3.0
Summary: Utilities to generate OpenAPI-compatible schema from API made with Django Rest Framework
Home-page: https://github.com/limdauto/drf_openapi
Author: Lim H.
Author-email: limdauto@gmail.com
License: MIT license
Keywords: drf_openapi
Platform: UNKNOWN
Classifier: Development Status :: 3 - Alpha
Classifier: Intended Audience :: Developers
Classifier: License :: OSI Approved :: MIT License
Classifier: Natural Language :: English
Classifier: Programming Language :: Python :: 2
Classifier: Programming Language :: Python :: 2.7
Classifier: Programming Language :: Python :: 3
Classifier: Programming Language :: Python :: 3.5
Classifier: Programming Language :: Python :: 3.6
Requires-Dist: Click (>=6.0)
Requires-Dist: django-rest-swagger (==2.1.2)
